[
{ "suicidios": 1, "state_code": 11, "mun_code": 1, "name": "Abasolo" },
{ "suicidios": 15, "state_code": 11, "mun_code": 2, "name": "Acámbaro" },   
{ "suicidios": 3, "state_code": 11, "mun_code": 3, "name": "Apaseo el Alto" },
{ "suicidios": 4, "state_code": 11, "mun_code": 4, "name": "Apaseo el Grande" },
{ "suicidios": 0, "state_code": 11, "mun_code": 5, "name": "Atarjea" }, 
{ "suicidios": 39, "state_code": 11, "mun_code": 6, "name": "Celaya" }, 
{ "suicidios": 8, "state_code": 11, "mun_code": 7, "name": "Comonfort" }, 
{ "suicidios": 2, "state_code": 11, "mun_code": 8, "name": "Coroneo" }, 
{ "suicidios": 9, "state_code": 11, "mun_code": 9, "name": "Cortazar" },  
{ "suicidios": 1, "state_code": 11, "mun_code": 10, "name": "Cuerámaro" }, 
{ "suicidios": 1, "state_code": 11, "mun_code": 11, "name": "Doctor Mora" }, 
{ "suicidios": 12, "state_code": 11, "mun_code": 12, "name": "Dolores Hidalgo"},
{ "suicidios": 26, "state_code": 11, "mun_code": 13, "name": "Guanajuato" }, 
{ "suicidios": 1, "state_code": 11, "mun_code": 14, "name": "Huanímaro" }, 
{ "suicidios": 45, "state_code": 11, "mun_code": 15, "name": "Irapuato" }, 
{ "suicidios": 6, "state_code": 11, "mun_code": 16, "name": "Jaral del Progreso" }, 
{ "suicidios": 2, "state_code": 11, "mun_code": 17, "name": "Jerécuaro" }, 
{ "suicidios": 138, "state_code": 11, "mun_code": 18, "name": "León" }, 
{ "suicidios": 5, "state_code": 11, "mun_code": 19, "name": "Manuel Doblado" }, 
{ "suicidios": 7, "state_code": 11, "mun_code": 20, "name": "Moroleón" }, 
{ "suicidios": 0, "state_code": 11, "mun_code": 21, "name": "Ocampo" }, 
{ "suicidios": 0, "state_code": 11, "mun_code": 22, "name": "Pueblo Nuevo" }, 
{ "suicidios": 6, "state_code": 11, "mun_code": 23, "name": "Purísima del Rincón" }, 
{ "suicidios": 5, "state_code": 11, "mun_code": 24, "name": "Pénjamo" },  
{ "suicidios": 3, "state_code": 11, "mun_code": 25, "name": "Romita" }, 
{ "suicidios": 17, "state_code": 11, "mun_code": 26, "name": "Salamanca" }, 
{ "suicidios": 6, "state_code": 11, "mun_code": 27, "name": "Salvatierra" }, 
{ "suicidios": 0, "state_code": 11, "mun_code": 28, "name": "San Diego de la Unión" },
{ "suicidios": 11, "state_code": 11, "mun_code": 29, "name": "San Felipe" },
{ "suicidios": 12, "state_code": 11, "mun_code": 30, "name": "San Francisco del Rincón"},
{ "suicidios": 8, "state_code": 11, "mun_code": 31, "name": "San José Iturbide" }, 
{ "suicidios": 12, "state_code": 11, "mun_code": 35, "name": "San Luis de la Paz" }, 
{ "suicidios": 21, "state_code": 11, "mun_code": 32, "name": "San Miguel de Allende"}, 
{ "suicidios": 1, "state_code": 11, "mun_code": 33, "name": "Santa Catarina" }, 
{ "suicidios": 12, "state_code": 11, "mun_code": 34, "name": "Santa Cruz de Juventino Rosas"},
{ "suicidios": 2, "state_code": 11, "mun_code": 36, "name": "Santiago Maravatío" }, 
{ "suicidios": 12, "state_code": 11, "mun_code": 37, "name": "Silao" }, 
{ "suicidios": 1, "state_code": 11, "mun_code": 38, "name": "Tarandacuao" }, 
{ "suicidios": 5, "state_code": 11, "mun_code": 39, "name": "Tarimoro" }, 
{ "suicidios": 0, "state_code": 11, "mun_code": 40, "name": "Tierra Blanca" }, 
{ "suicidios": 6, "state_code": 11, "mun_code": 41, "name": "Uriangato" }, 
{ "suicidios": 11, "state_code": 11, "mun_code": 42, "name": "Valle de Santiago" }, 
{ "suicidios": 4, "state_code": 11, "mun_code": 43, "name": "Victoria" }, 
{ "suicidios": 7, "state_code": 11, "mun_code": 44, "name": "Villagrán" }, 
{ "suicidios": 0, "state_code": 11, "mun_code": 45, "name": "Xichú" },  
{ "suicidios": 5, "state_code": 11, "mun_code": 46, "name": "Yuriria" }
]